mseep_tdengine_mcp_server-0.0.10.dist-info/licenses/LICENSE
tdengine_mcp_server/__init__.py
tdengine_mcp_server/__main__.py
tdengine_mcp_server/py.typed
tdengine_mcp_server/server.py
tdengine_mcp_server/template.py
mseep_tdengine_mcp_server-0.0.10.dist-info/METADATA
mseep_tdengine_mcp_server-0.0.10.dist-info/WHEEL
mseep_tdengine_mcp_server-0.0.10.dist-info/entry_points.txt
mseep_tdengine_mcp_server-0.0.10.dist-info/top_level.txt
mseep_tdengine_mcp_server-0.0.10.dist-info/RECORD
