Metadata-Version: 2.4
Name: mseep-tdengine-mcp-server
Version: 0.0.10
Summary: Add your description here
Author-email: mseep <support@skydeck.ai>
Requires-Python: >=3.12
License-File: LICENSE
Requires-Dist: jinja2
Requires-Dist: mcp[cli]
Requires-Dist: taospy
Dynamic: license-file
